sgmse/__init__.py
sgmse/data_module.py
sgmse/model.py
sgmse/sdes.py
sgmse/backbones/__init__.py
sgmse/backbones/dcunet.py
sgmse/backbones/ncsnpp.py
sgmse/backbones/ncsnpp_48k.py
sgmse/backbones/ncsnpp_v2.py
sgmse/backbones/shared.py
sgmse/backbones/ncsnpp_utils/__init__.py
sgmse/backbones/ncsnpp_utils/layers.py
sgmse/backbones/ncsnpp_utils/layerspp.py
sgmse/backbones/ncsnpp_utils/normalization.py
sgmse/backbones/ncsnpp_utils/up_or_down_sampling.py
sgmse/backbones/ncsnpp_utils/utils.py
sgmse/backbones/ncsnpp_utils/op/__init__.py
sgmse/backbones/ncsnpp_utils/op/fused_act.py
sgmse/backbones/ncsnpp_utils/op/upfirdn2d.py
sgmse/sampling/__init__.py
sgmse/sampling/correctors.py
sgmse/sampling/predictors.py
sgmse/util/__init__.py
sgmse/util/inference.py
sgmse/util/other.py
sgmse/util/registry.py
sgmse/util/tensors.py
sgmse-0.1.2.dist-info/LICENSE
sgmse-0.1.2.dist-info/METADATA
sgmse-0.1.2.dist-info/WHEEL
sgmse-0.1.2.dist-info/top_level.txt
sgmse-0.1.2.dist-info/RECORD
