Metadata-Version: 2.1
Name: sgmse
Version: 0.1.2
Summary: Speech enhancement model using SGMSE
Home-page: https://github.com/sp-uhh/sgmse
Author: Signal Processing (SP), Universität Hamburg
Author-email: sp-office.inf@uni-hamburg.de
License: MIT
Project-URL: Source Code, https://github.com/sp-uhh/sgmse
Classifier: Programming Language :: Python :: 3
Classifier: License :: OSI Approved :: MIT License
Classifier: Operating System :: OS Independent
Requires-Python: >=3.6
License-File: LICENSE
Requires-Dist: gdown
Requires-Dist: h5py
Requires-Dist: ipympl
Requires-Dist: librosa
Requires-Dist: ninja
Requires-Dist: numpy (<2.0)
Requires-Dist: pandas
Requires-Dist: pesq
Requires-Dist: pillow
Requires-Dist: protobuf
Requires-Dist: pyarrow
Requires-Dist: pyroomacoustics
Requires-Dist: pystoi
Requires-Dist: pytorch-lightning
Requires-Dist: scipy
Requires-Dist: sdeint
Requires-Dist: setuptools
Requires-Dist: seaborn
Requires-Dist: torch
Requires-Dist: torch-ema
Requires-Dist: torch-pesq
Requires-Dist: torchaudio
Requires-Dist: torchvision
Requires-Dist: torchinfo
Requires-Dist: torchsde
Requires-Dist: tqdm
Requires-Dist: wandb
